{
  "id": "rss-20260604-008",
  "title": "Thinking Through Signs: PEEL as a Semiotic Scaffolding for Epistemically Accountable AI-Enabled Research",
  "source": "rss:arXiv cs.AI",
  "source_url": "https://arxiv.org/abs/2606.04152",
  "author": "arXiv cs.AI",
  "published_at": "2026-06-04T11:01:04.060656+00:00",
  "collected_at": "2026-06-04T11:01:04.060656+00:00",
  "summary": "该论文提出PEEL框架，作为符号学脚手架，用于增强AI驱动研究的认知责任性。核心价值在于通过符号学方法提升AI系统的可解释性和可信度。",
  "score": 7,
  "tags": [
    "reasoning",
    "evaluation"
  ],
  "audience": "intermediate",
  "status": "review",
  "updated_at": "2026-06-04T11:02:08.186906+00:00"
}