{
  "id": "rss-20260430-002",
  "title": "Google and Pentagon reportedly agree on deal for 'any lawful' use of AI",
  "source": "rss:Hacker News (Best)",
  "source_url": "https://www.theverge.com/ai-artificial-intelligence/919494/google-pentagon-classified-ai-deal",
  "author": "Hacker News (Best)",
  "published_at": "2026-04-30T08:56:43.488931+00:00",
  "collected_at": "2026-04-30T08:56:43.488931+00:00",
  "summary": "Google与美国国防部达成协议，允许在遵守法律的前提下使用AI技术。该合作可能涉及军事应用，引发对AI伦理和使用的广泛讨论。",
  "score": 7,
  "tags": [
    "security",
    "deployment"
  ],
  "audience": "intermediate",
  "status": "review",
  "updated_at": "2026-04-30T08:58:03.306055+00:00"
}