{
  "id": "rss-20260416-020",
  "title": "Reward Design for Physical Reasoning in Vision-Language Models",
  "source": "rss:arXiv cs.AI",
  "source_url": "https://arxiv.org/abs/2604.13993",
  "author": "arXiv cs.AI",
  "published_at": "2026-04-16T08:44:37.345494+00:00",
  "collected_at": "2026-04-16T08:44:37.345494+00:00",
  "summary": "该研究探讨了如何为视觉语言模型设计奖励机制，以提升其在物理推理任务中的表现。通过优化奖励函数，旨在增强模型对物理世界的理解和推理能力。这项工作对于推动具身智能和复杂场景理解具有重要价值。",
  "score": 7,
  "tags": [
    "vision",
    "reasoning",
    "fine-tuning"
  ],
  "audience": "intermediate",
  "status": "review",
  "updated_at": "2026-04-16T08:48:47.823456+00:00"
}