{
  "id": "rss-20260716-004",
  "title": "SPINE: Bridging the Cyber-Physical Gap with Agentic AI",
  "source": "rss:arXiv cs.AI",
  "source_url": "https://arxiv.org/abs/2607.13049",
  "author": "arXiv cs.AI",
  "published_at": "2026-07-16T10:01:17.354660+00:00",
  "collected_at": "2026-07-16T10:01:17.354660+00:00",
  "summary": "SPINE提出了一种基于代理AI的框架，旨在弥合网络空间与物理世界之间的鸿沟，通过智能体实现自主决策与物理系统交互。该技术核心价值在于提升工业自动化与物联网场景中的实时响应与适应性。",
  "score": 7,
  "tags": [
    "agent",
    "multi-agent",
    "reasoning"
  ],
  "audience": "intermediate",
  "status": "review",
  "updated_at": "2026-07-16T10:02:18.037139+00:00"
}