{
  "id": "rss-20260424-003",
  "title": "AI to Learn 2.0: A Deliverable-Oriented Governance Framework and Maturity Rubric for Opaque AI in Learning-Intensive Domains",
  "source": "rss:arXiv cs.AI",
  "source_url": "https://arxiv.org/abs/2604.19751",
  "author": "arXiv cs.AI",
  "published_at": "2026-04-24T08:51:43.485521+00:00",
  "collected_at": "2026-04-24T08:51:43.485521+00:00",
  "summary": "该论文提出了一种面向交付的治理框架和成熟度评估工具，用于在密集型学习领域中管理不透明AI系统。其核心价值在于为AI在教育、医疗等高风险领域的应用提供了可操作的评估标准和治理指南。",
  "score": 7,
  "tags": [
    "evaluation",
    "security"
  ],
  "audience": "intermediate",
  "status": "review",
  "updated_at": "2026-04-24T08:52:59.257970+00:00"
}